csync/__init__.py
csync/_version.py
csync/watcher.py
csync-0.1.dist-info/LICENSE
csync-0.1.dist-info/METADATA
csync-0.1.dist-info/WHEEL
csync-0.1.dist-info/entry_points.txt
csync-0.1.dist-info/top_level.txt
csync-0.1.dist-info/RECORD
