Metadata-Version: 2.1
Name: csync
Version: 0.1
Summary: Syncs code to machines on code changes
Home-page: https://github.com/s1113950/csync.git
Author: Steven Robertson
License: UNKNOWN
Platform: UNKNOWN
Classifier: Development Status :: 3 - Alpha
Classifier: Environment :: Console
Classifier: Intended Audience :: End Users/Desktop
Classifier: Intended Audience :: Developers
Classifier: Operating System :: POSIX
Classifier: Operating System :: MacOS :: MacOS X
Classifier: Programming Language :: Python :: 3
Requires-Dist: configparser (==3.5.0)
Requires-Dist: watchdog (==0.8.3)
